langchain_references/__init__.py
langchain_references/references.py
langchain_references-1.0.0.dist-info/METADATA
langchain_references-1.0.0.dist-info/WHEEL
langchain_references-1.0.0.dist-info/licenses/LICENSE.txt
langchain_references-1.0.0.dist-info/RECORD
