Metadata-Version: 2.4
Name: langchain-references
Version: 1.0.0
Summary: Component to manager referenced documents with LLM.
Project-URL: Homepage, https://www.github.com/pprados/langchain-references
Project-URL: Repository, https://www.github.com/pprados/langchain-references
Author: Philippe PRADOS
License: Apache-2.0
License-File: LICENSE.txt
Requires-Python: <4.0,>=3.10
Requires-Dist: langchain-core>=1.0.0
